{"schema":{"fields":[{"name":"index","type":"integer"},{"name":"DateTime","type":"string"},{"name":"Country","type":"string"},{"name":"Total","type":"string"},{"name":"New","type":"string"},{"name":"Deaths","type":"string"},{"name":"NewDeath","type":"string"},{"name":"Recovered","type":"string"},{"name":"Active","type":"string"},{"name":"Critical","type":"string"},{"name":"TotalPerM","type":"string"},{"name":"TDeathPerM","type":"string"},{"name":"Tests","type":"string"},{"name":"TestPerM","type":"string"}],"primaryKey":["index"],"pandas_version":"0.20.0"},"data":[{"index":0,"DateTime":"2020\/06\/14,04:02:10","Country":"\nNorth America\n","Total":"2459117","New":"4551","Deaths":"144586","NewDeath":"450","Recovered":"1054934","Active":"3363","Critical":"1259597","TotalPerM":"19441","TDeathPerM":0,"Tests":0,"TestPerM":0},{"index":1,"DateTime":"2020\/06\/14,04:02:10","Country":"\nSouth America\n","Total":"1393063","New":"913","Deaths":"59331","NewDeath":"26","Recovered":"743229","Active":"10239","Critical":"590503","TotalPerM":"12001","TDeathPerM":0,"Tests":0,"TestPerM":0},{"index":2,"DateTime":"2020\/06\/14,04:02:10","Country":"\nEurope\n","Total":"2190153","New":0,"Deaths":"182579","NewDeath":0,"Recovered":"1158327","Active":0,"Critical":"849247","TotalPerM":"6708","TDeathPerM":0,"Tests":0,"TestPerM":0},{"index":3,"DateTime":"2020\/06\/14,04:02:10","Country":"\nAsia\n","Total":"1578027","New":"355","Deaths":"39476","NewDeath":0,"Recovered":"966334","Active":"313","Critical":"572217","TotalPerM":"15426","TDeathPerM":0,"Tests":0,"TestPerM":0},{"index":4,"DateTime":"2020\/06\/14,04:02:10","Country":"\nAfrica\n","Total":"235704","New":0,"Deaths":"6283","NewDeath":0,"Recovered":"108837","Active":"2","Critical":"120584","TotalPerM":"524","TDeathPerM":0,"Tests":0,"TestPerM":0},{"index":5,"DateTime":"2020\/06\/14,04:02:10","Country":"\nOceania\n","Total":"8931","New":"18","Deaths":"124","NewDeath":0,"Recovered":"8403","Active":"3","Critical":"404","TotalPerM":"2","TDeathPerM":0,"Tests":0,"TestPerM":0},{"index":6,"DateTime":"2020\/06\/14,04:02:10","Country":"\n\n","Total":"721","New":0,"Deaths":"15","NewDeath":0,"Recovered":"651","Active":0,"Critical":"55","TotalPerM":"4","TDeathPerM":0,"Tests":0,"TestPerM":0},{"index":7,"DateTime":"2020\/06\/14,04:02:10","Country":"World","Total":"7865716","New":"5837","Deaths":"432394","NewDeath":"476","Recovered":"4040715","Active":"13920","Critical":"3392607","TotalPerM":"54106","TDeathPerM":"1009","Tests":"55.5","TestPerM":0},{"index":8,"DateTime":"2020\/06\/14,04:02:10","Country":"USA","Total":"2142224","New":0,"Deaths":"117527 ","NewDeath":0,"Recovered":"854106","Active":0,"Critical":"1170591","TotalPerM":"16744","TDeathPerM":"6474","Tests":"355","TestPerM":"24292171"},{"index":9,"DateTime":"2020\/06\/14,04:02:10","Country":"Brazil","Total":"850796","New":0,"Deaths":"42791 ","NewDeath":0,"Recovered":"437512","Active":"9902","Critical":"370493","TotalPerM":"8318","TDeathPerM":"4004","Tests":"201","TestPerM":"1499041"},{"index":10,"DateTime":"2020\/06\/14,04:02:10","Country":"Russia","Total":"520129","New":0,"Deaths":"6829 ","NewDeath":0,"Recovered":"274641","Active":0,"Critical":"238659","TotalPerM":"2300","TDeathPerM":"3564","Tests":"47","TestPerM":"14574117"},{"index":11,"DateTime":"2020\/06\/14,04:02:10","Country":"India","Total":"321626","New":0,"Deaths":"9199 ","NewDeath":0,"Recovered":"162379","Active":"53","Critical":"150048","TotalPerM":"8944","TDeathPerM":"233","Tests":"7","TestPerM":"5507182"},{"index":12,"DateTime":"2020\/06\/14,04:02:10","Country":"UK","Total":"294375","New":0,"Deaths":"41662 ","NewDeath":0,"Recovered":"N\/A","Active":"N\/A","Critical":"N\/A","TotalPerM":"492","TDeathPerM":"4337","Tests":"614","TestPerM":"6624676"},{"index":13,"DateTime":"2020\/06\/14,04:02:10","Country":"Spain","Total":"290685","New":0,"Deaths":"27136 ","NewDeath":0,"Recovered":"N\/A","Active":"N\/A","Critical":"N\/A","TotalPerM":"617","TDeathPerM":"6217","Tests":"580","TestPerM":"4465338"},{"index":14,"DateTime":"2020\/06\/14,04:02:10","Country":"Italy","Total":"236651","New":0,"Deaths":"34301 ","NewDeath":0,"Recovered":"174865","Active":0,"Critical":"27485","TotalPerM":"220","TDeathPerM":"3914","Tests":"567","TestPerM":"4564191"},{"index":15,"DateTime":"2020\/06\/14,04:02:10","Country":"Peru","Total":"225132","New":0,"Deaths":"6498 ","NewDeath":0,"Recovered":"111724","Active":0,"Critical":"106910","TotalPerM":"1113","TDeathPerM":"6833","Tests":"197","TestPerM":"1338477"},{"index":16,"DateTime":"2020\/06\/14,04:02:10","Country":"Germany","Total":"187423","New":0,"Deaths":"8867 ","NewDeath":0,"Recovered":"171900","Active":0,"Critical":"6656","TotalPerM":"447","TDeathPerM":"2237","Tests":"106","TestPerM":"4694147"},{"index":17,"DateTime":"2020\/06\/14,04:02:10","Country":"Iran","Total":"184955","New":0,"Deaths":"8730 ","NewDeath":0,"Recovered":"146748","Active":0,"Critical":"29477","TotalPerM":"2755","TDeathPerM":"2203","Tests":"104","TestPerM":"1219400"},{"index":18,"DateTime":"2020\/06\/14,04:02:10","Country":"Turkey","Total":"176677","New":0,"Deaths":"4792 ","NewDeath":0,"Recovered":"150087","Active":0,"Critical":"21798","TotalPerM":"684","TDeathPerM":"2096","Tests":"57","TestPerM":"2586995"},{"index":19,"DateTime":"2020\/06\/14,04:02:10","Country":"Chile","Total":"167355","New":0,"Deaths":"3101 ","NewDeath":0,"Recovered":"137296","Active":0,"Critical":"26958","TotalPerM":"1656","TDeathPerM":"8758","Tests":"162","TestPerM":"819999"},{"index":20,"DateTime":"2020\/06\/14,04:02:10","Country":"France","Total":"156813","New":0,"Deaths":"29398 ","NewDeath":0,"Recovered":"72808","Active":0,"Critical":"54607","TotalPerM":"871","TDeathPerM":"2403","Tests":"450","TestPerM":"1384633"},{"index":21,"DateTime":"2020\/06\/14,04:02:10","Country":"Mexico","Total":"142690","New":"3494","Deaths":"16872 ","NewDeath":"424","Recovered":"104975","Active":"3208","Critical":"20843","TotalPerM":"378","TDeathPerM":"1107","Tests":"131","TestPerM":"401755"},{"index":22,"DateTime":"2020\/06\/14,04:02:10","Country":"Pakistan","Total":"132405","New":0,"Deaths":"2551 ","NewDeath":0,"Recovered":"50056","Active":0,"Critical":"79798","TotalPerM":"111","TDeathPerM":"600","Tests":"12","TestPerM":"839019"},{"index":23,"DateTime":"2020\/06\/14,04:02:10","Country":"Saudi Arabia","Total":"123308","New":0,"Deaths":"932 ","NewDeath":0,"Recovered":"82548","Active":0,"Critical":"39828","TotalPerM":"1843","TDeathPerM":"3545","Tests":"27","TestPerM":"1087021"},{"index":24,"DateTime":"2020\/06\/14,04:02:10","Country":"Canada","Total":"98410","New":0,"Deaths":"8107 ","NewDeath":0,"Recovered":"59354","Active":0,"Critical":"30949","TotalPerM":"1937","TDeathPerM":"2609","Tests":"215","TestPerM":"2113924"},{"index":25,"DateTime":"2020\/06\/14,04:02:10","Country":"Bangladesh","Total":"84379","New":0,"Deaths":"1139 ","NewDeath":0,"Recovered":"17828","Active":0,"Critical":"65412","TotalPerM":"1","TDeathPerM":"513","Tests":"7","TestPerM":"489960"},{"index":26,"DateTime":"2020\/06\/14,04:02:10","Country":"Qatar","Total":"78416","New":0,"Deaths":"70 ","NewDeath":0,"Recovered":"55252","Active":0,"Critical":"23094","TotalPerM":"232","TDeathPerM":"27928","Tests":"25","TestPerM":"286830"},{"index":27,"DateTime":"2020\/06\/14,04:02:10","Country":"South Africa","Total":"65736","New":0,"Deaths":"1423 ","NewDeath":0,"Recovered":"36850","Active":0,"Critical":"27463","TotalPerM":"208","TDeathPerM":"1109","Tests":"24","TestPerM":"1087887"},{"index":28,"DateTime":"2020\/06\/14,04:02:10","Country":"Belgium","Total":"59918","New":0,"Deaths":"9650 ","NewDeath":0,"Recovered":"16547","Active":0,"Critical":"33721","TotalPerM":"88","TDeathPerM":"5171","Tests":"833","TestPerM":"1010059"},{"index":29,"DateTime":"2020\/06\/14,04:02:10","Country":"Belarus","Total":"53241","New":0,"Deaths":"303 ","NewDeath":0,"Recovered":"29111","Active":0,"Critical":"23827","TotalPerM":"92","TDeathPerM":"5634","Tests":"32","TestPerM":"714324"},{"index":30,"DateTime":"2020\/06\/14,04:02:10","Country":"Sweden","Total":"50931","New":0,"Deaths":"4874 ","NewDeath":0,"Recovered":"N\/A","Active":"N\/A","Critical":"N\/A","TotalPerM":"272","TDeathPerM":"5045","Tests":"483","TestPerM":"325000"},{"index":31,"DateTime":"2020\/06\/14,04:02:10","Country":"Colombia","Total":"48746","New":0,"Deaths":"1592 ","NewDeath":0,"Recovered":"19426","Active":0,"Critical":"27728","TotalPerM":"335","TDeathPerM":"959","Tests":"31","TestPerM":"482832"},{"index":32,"DateTime":"2020\/06\/14,04:02:10","Country":"Netherlands","Total":"48640","New":0,"Deaths":"6057 ","NewDeath":0,"Recovered":"N\/A","Active":"N\/A","Critical":"N\/A","TotalPerM":"77","TDeathPerM":"2839","Tests":"354","TestPerM":"455067"},{"index":33,"DateTime":"2020\/06\/14,04:02:10","Country":"Ecuador","Total":"46356","New":0,"Deaths":"3874 ","NewDeath":0,"Recovered":"22865","Active":0,"Critical":"19617","TotalPerM":"219","TDeathPerM":"2629","Tests":"220","TestPerM":"134141"},{"index":34,"DateTime":"2020\/06\/14,04:02:10","Country":"Egypt","Total":"42980","New":0,"Deaths":"1484 ","NewDeath":0,"Recovered":"11529","Active":0,"Critical":"29967","TotalPerM":"41","TDeathPerM":"420","Tests":"15","TestPerM":"135000"},{"index":35,"DateTime":"2020\/06\/14,04:02:10","Country":"UAE","Total":"41990","New":0,"Deaths":"288 ","NewDeath":0,"Recovered":"26761","Active":0,"Critical":"14941","TotalPerM":"1","TDeathPerM":"4248","Tests":"29","TestPerM":"2626000"},{"index":36,"DateTime":"2020\/06\/14,04:02:10","Country":"Singapore","Total":"40197","New":0,"Deaths":"26 ","NewDeath":0,"Recovered":"28808","Active":0,"Critical":"11363","TotalPerM":"1","TDeathPerM":"6873","Tests":"4","TestPerM":"488695"},{"index":37,"DateTime":"2020\/06\/14,04:02:10","Country":"Indonesia","Total":"37420","New":0,"Deaths":"2091 ","NewDeath":0,"Recovered":"13776","Active":0,"Critical":"21553","TotalPerM":0,"TDeathPerM":"137","Tests":"8","TestPerM":"495527"},{"index":38,"DateTime":"2020\/06\/14,04:02:10","Country":"Portugal","Total":"36463","New":0,"Deaths":"1512 ","NewDeath":0,"Recovered":"22438","Active":0,"Critical":"12513","TotalPerM":"77","TDeathPerM":"3576","Tests":"148","TestPerM":"975737"},{"index":39,"DateTime":"2020\/06\/14,04:02:10","Country":"Kuwait","Total":"35466","New":0,"Deaths":"289 ","NewDeath":0,"Recovered":"25882","Active":0,"Critical":"9295","TotalPerM":"176","TDeathPerM":"8311","Tests":"68","TestPerM":"332288"},{"index":40,"DateTime":"2020\/06\/14,04:02:10","Country":"Switzerland","Total":"31094","New":0,"Deaths":"1938 ","NewDeath":0,"Recovered":"28800","Active":0,"Critical":"356","TotalPerM":"15","TDeathPerM":"3594","Tests":"224","TestPerM":"453745"},{"index":41,"DateTime":"2020\/06\/14,04:02:10","Country":"Ukraine","Total":"30506","New":0,"Deaths":"880 ","NewDeath":0,"Recovered":"13976","Active":0,"Critical":"15650","TotalPerM":"306","TDeathPerM":"697","Tests":"20","TestPerM":"479111"},{"index":42,"DateTime":"2020\/06\/14,04:02:10","Country":"Argentina","Total":"30295","New":0,"Deaths":"815 ","NewDeath":0,"Recovered":"9083","Active":0,"Critical":"20397","TotalPerM":"274","TDeathPerM":"671","Tests":"18","TestPerM":"228324"},{"index":43,"DateTime":"2020\/06\/14,04:02:10","Country":"Poland","Total":"29017","New":0,"Deaths":"1237 ","NewDeath":0,"Recovered":"14104","Active":0,"Critical":"13676","TotalPerM":"77","TDeathPerM":"767","Tests":"33","TestPerM":"1169088"},{"index":44,"DateTime":"2020\/06\/14,04:02:10","Country":"Philippines","Total":"25392","New":0,"Deaths":"1074 ","NewDeath":0,"Recovered":"5706","Active":0,"Critical":"18612","TotalPerM":"82","TDeathPerM":"232","Tests":"10","TestPerM":"495529"},{"index":45,"DateTime":"2020\/06\/14,04:02:10","Country":"Ireland","Total":"25295","New":0,"Deaths":"1705 ","NewDeath":0,"Recovered":"22698","Active":0,"Critical":"892","TotalPerM":"28","TDeathPerM":"5126","Tests":"345","TestPerM":"367780"},{"index":46,"DateTime":"2020\/06\/14,04:02:10","Country":"Afghanistan","Total":"24102","New":0,"Deaths":"451 ","NewDeath":0,"Recovered":"4201","Active":0,"Critical":"19450","TotalPerM":"19","TDeathPerM":"620","Tests":"12","TestPerM":"54770"},{"index":47,"DateTime":"2020\/06\/14,04:02:10","Country":"Dominican Republic","Total":"22572","New":0,"Deaths":"577 ","NewDeath":0,"Recovered":"13084","Active":0,"Critical":"8911","TotalPerM":"124","TDeathPerM":"2082","Tests":"53","TestPerM":"107175"},{"index":48,"DateTime":"2020\/06\/14,04:02:10","Country":"Oman","Total":"22077","New":0,"Deaths":"99 ","NewDeath":0,"Recovered":"7530","Active":0,"Critical":"14448","TotalPerM":"94","TDeathPerM":"4329","Tests":"19","TestPerM":"136164"},{"index":49,"DateTime":"2020\/06\/14,04:02:10","Country":"Romania","Total":"21679","New":0,"Deaths":"1394 ","NewDeath":0,"Recovered":"15635","Active":0,"Critical":"4650","TotalPerM":"171","TDeathPerM":"1127","Tests":"72","TestPerM":"552670"},{"index":50,"DateTime":"2020\/06\/14,04:02:10","Country":"Panama","Total":"20059","New":0,"Deaths":"429 ","NewDeath":0,"Recovered":"13759","Active":0,"Critical":"5871","TotalPerM":"96","TDeathPerM":"4653","Tests":"100","TestPerM":"89736"},{"index":51,"DateTime":"2020\/06\/14,04:02:10","Country":"Israel","Total":"18972","New":0,"Deaths":"300 ","NewDeath":0,"Recovered":"15357","Active":0,"Critical":"3315","TotalPerM":"33","TDeathPerM":"2063","Tests":"33","TestPerM":"739627"},{"index":52,"DateTime":"2020\/06\/14,04:02:10","Country":"Iraq","Total":"18950","New":0,"Deaths":"549 ","NewDeath":0,"Recovered":"7515","Active":0,"Critical":"10886","TotalPerM":"111","TDeathPerM":"472","Tests":"14","TestPerM":"359950"},{"index":53,"DateTime":"2020\/06\/14,04:02:10","Country":"Bolivia","Total":"17842","New":"913","Deaths":"585 ","NewDeath":"26","Recovered":"2768","Active":"337","Critical":"14489","TotalPerM":"71","TDeathPerM":"1530","Tests":"50","TestPerM":"42741"},{"index":54,"DateTime":"2020\/06\/14,04:02:10","Country":"Bahrain","Total":"17713","New":0,"Deaths":"37 ","NewDeath":0,"Recovered":"12191","Active":0,"Critical":"5485","TotalPerM":"12","TDeathPerM":"10432","Tests":"22","TestPerM":"410842"},{"index":55,"DateTime":"2020\/06\/14,04:02:10","Country":"Japan","Total":"17382","New":0,"Deaths":"924 ","NewDeath":0,"Recovered":"15580","Active":0,"Critical":"878","TotalPerM":"76","TDeathPerM":"137","Tests":"7","TestPerM":"336161"},{"index":56,"DateTime":"2020\/06\/14,04:02:10","Country":"Austria","Total":"17078","New":0,"Deaths":"677 ","NewDeath":0,"Recovered":"16012","Active":0,"Critical":"389","TotalPerM":"11","TDeathPerM":"1897","Tests":"75","TestPerM":"520976"},{"index":57,"DateTime":"2020\/06\/14,04:02:10","Country":"Armenia","Total":"16004","New":0,"Deaths":"264 ","NewDeath":0,"Recovered":"6081","Active":0,"Critical":"9659","TotalPerM":"10","TDeathPerM":"5401","Tests":"89","TestPerM":"80130"},{"index":58,"DateTime":"2020\/06\/14,04:02:10","Country":"Nigeria","Total":"15682","New":0,"Deaths":"407 ","NewDeath":0,"Recovered":"5101","Active":0,"Critical":"10174","TotalPerM":"7","TDeathPerM":"76","Tests":"2","TestPerM":"90464"},{"index":59,"DateTime":"2020\/06\/14,04:02:10","Country":"Kazakhstan","Total":"14496","New":"258","Deaths":"73 ","NewDeath":0,"Recovered":"9056","Active":"227","Critical":"5367","TotalPerM":"77","TDeathPerM":"772","Tests":"4","TestPerM":"1135407"},{"index":60,"DateTime":"2020\/06\/14,04:02:10","Country":"Serbia","Total":"12251","New":0,"Deaths":"253 ","NewDeath":0,"Recovered":"11348","Active":0,"Critical":"650","TotalPerM":"15","TDeathPerM":"1402","Tests":"29","TestPerM":"301126"},{"index":61,"DateTime":"2020\/06\/14,04:02:10","Country":"Denmark","Total":"12139","New":0,"Deaths":"597 ","NewDeath":0,"Recovered":"11035","Active":0,"Critical":"507","TotalPerM":"11","TDeathPerM":"2096","Tests":"103","TestPerM":"786198"},{"index":62,"DateTime":"2020\/06\/14,04:02:10","Country":"S. Korea","Total":"12085","New":"34","Deaths":"277 ","NewDeath":0,"Recovered":"10718","Active":"27","Critical":"1090","TotalPerM":"15","TDeathPerM":"236","Tests":"5","TestPerM":"1100328"},{"index":63,"DateTime":"2020\/06\/14,04:02:10","Country":"Moldova","Total":"11459","New":0,"Deaths":"398 ","NewDeath":0,"Recovered":"6421","Active":0,"Critical":"4640","TotalPerM":"378","TDeathPerM":"2840","Tests":"99","TestPerM":"63328"},{"index":64,"DateTime":"2020\/06\/14,04:02:10","Country":"Ghana","Total":"11118","New":0,"Deaths":"48 ","NewDeath":0,"Recovered":"3979","Active":0,"Critical":"7091","TotalPerM":"4","TDeathPerM":"358","Tests":"2","TestPerM":"245448"},{"index":65,"DateTime":"2020\/06\/14,04:02:10","Country":"Algeria","Total":"10810","New":0,"Deaths":"760 ","NewDeath":0,"Recovered":"7420","Active":0,"Critical":"2630","TotalPerM":"39","TDeathPerM":"247","Tests":"17","TestPerM":0},{"index":66,"DateTime":"2020\/06\/14,04:02:10","Country":"Czechia","Total":"9991","New":0,"Deaths":"328 ","NewDeath":0,"Recovered":"7219","Active":0,"Critical":"2444","TotalPerM":"14","TDeathPerM":"933","Tests":"31","TestPerM":"494805"},{"index":67,"DateTime":"2020\/06\/14,04:02:10","Country":"Azerbaijan","Total":"9570","New":0,"Deaths":"115 ","NewDeath":0,"Recovered":"5309","Active":0,"Critical":"4146","TotalPerM":"66","TDeathPerM":"944","Tests":"11","TestPerM":"362654"},{"index":68,"DateTime":"2020\/06\/14,04:02:10","Country":"Guatemala","Total":"9491","New":"509","Deaths":"367 ","NewDeath":"16","Recovered":"1804","Active":"102","Critical":"7320","TotalPerM":"5","TDeathPerM":"530","Tests":"21","TestPerM":"31427"},{"index":69,"DateTime":"2020\/06\/14,04:02:10","Country":"Morocco","Total":"8692","New":0,"Deaths":"212 ","NewDeath":0,"Recovered":"7696","Active":0,"Critical":"784","TotalPerM":"7","TDeathPerM":"236","Tests":"6","TestPerM":"405898"},{"index":70,"DateTime":"2020\/06\/14,04:02:10","Country":"Cameroon","Total":"8681","New":0,"Deaths":"212 ","NewDeath":0,"Recovered":"4836","Active":0,"Critical":"3633","TotalPerM":"28","TDeathPerM":"327","Tests":"8","TestPerM":0},{"index":71,"DateTime":"2020\/06\/14,04:02:10","Country":"Norway","Total":"8628","New":0,"Deaths":"242 ","NewDeath":0,"Recovered":"8138","Active":0,"Critical":"248","TotalPerM":"5","TDeathPerM":"1592","Tests":"45","TestPerM":"277253"},{"index":72,"DateTime":"2020\/06\/14,04:02:10","Country":"Honduras","Total":"8455","New":"323","Deaths":"310 ","NewDeath":"4","Recovered":"894","Active":"50","Critical":"7251","TotalPerM":"13","TDeathPerM":"854","Tests":"31","TestPerM":"21540"},{"index":73,"DateTime":"2020\/06\/14,04:02:10","Country":"Malaysia","Total":"8445","New":0,"Deaths":"120 ","NewDeath":0,"Recovered":"7311","Active":0,"Critical":"1014","TotalPerM":"4","TDeathPerM":"261","Tests":"4","TestPerM":"618360"},{"index":74,"DateTime":"2020\/06\/14,04:02:10","Country":"Australia","Total":"7320","New":"18","Deaths":"102 ","NewDeath":0,"Recovered":"6815","Active":"3","Critical":"403","TotalPerM":"2","TDeathPerM":"287","Tests":"4","TestPerM":"1804533"},{"index":75,"DateTime":"2020\/06\/14,04:02:10","Country":"Finland","Total":"7087","New":0,"Deaths":"325 ","NewDeath":0,"Recovered":"6200","Active":0,"Critical":"562","TotalPerM":"2","TDeathPerM":"1279","Tests":"59","TestPerM":"217300"},{"index":76,"DateTime":"2020\/06\/14,04:02:10","Country":"Sudan","Total":"7007","New":0,"Deaths":"447 ","NewDeath":0,"Recovered":"2556","Active":0,"Critical":"4004","TotalPerM":0,"TDeathPerM":"160","Tests":"10","TestPerM":"401"},{"index":77,"DateTime":"2020\/06\/14,04:02:10","Country":"Nepal","Total":"5335","New":0,"Deaths":"18 ","NewDeath":0,"Recovered":"913","Active":0,"Critical":"4404","TotalPerM":0,"TDeathPerM":"183","Tests":"0.6","TestPerM":"317870"},{"index":78,"DateTime":"2020\/06\/14,04:02:10","Country":"Senegal","Total":"4996","New":0,"Deaths":"60 ","NewDeath":0,"Recovered":"3228","Active":0,"Critical":"1708","TotalPerM":"23","TDeathPerM":"299","Tests":"4","TestPerM":"59008"},{"index":79,"DateTime":"2020\/06\/14,04:02:10","Country":"Tajikistan","Total":"4971","New":0,"Deaths":"50 ","NewDeath":0,"Recovered":"3288","Active":0,"Critical":"1633","TotalPerM":0,"TDeathPerM":"522","Tests":"5","TestPerM":0},{"index":80,"DateTime":"2020\/06\/14,04:02:10","Country":"Uzbekistan","Total":"4966","New":0,"Deaths":"19 ","NewDeath":0,"Recovered":"3874","Active":0,"Critical":"1073","TotalPerM":"16","TDeathPerM":"148","Tests":"0.6","TestPerM":"748555"},{"index":81,"DateTime":"2020\/06\/14,04:02:10","Country":"Ivory Coast","Total":"4848","New":0,"Deaths":"45 ","NewDeath":0,"Recovered":"2397","Active":0,"Critical":"2406","TotalPerM":0,"TDeathPerM":"184","Tests":"2","TestPerM":"35935"},{"index":82,"DateTime":"2020\/06\/14,04:02:10","Country":"DRC","Total":"4724","New":0,"Deaths":"106 ","NewDeath":0,"Recovered":"595","Active":0,"Critical":"4023","TotalPerM":0,"TDeathPerM":"53","Tests":"1","TestPerM":0},{"index":83,"DateTime":"2020\/06\/14,04:02:10","Country":"Guinea","Total":"4484","New":0,"Deaths":"25 ","NewDeath":0,"Recovered":"3213","Active":0,"Critical":"1246","TotalPerM":"24","TDeathPerM":"342","Tests":"2","TestPerM":"14407"},{"index":84,"DateTime":"2020\/06\/14,04:02:10","Country":"Djibouti","Total":"4449","New":0,"Deaths":"41 ","NewDeath":0,"Recovered":"2823","Active":0,"Critical":"1585","TotalPerM":0,"TDeathPerM":"4506","Tests":"42","TestPerM":"40855"},{"index":85,"DateTime":"2020\/06\/14,04:02:10","Country":"Haiti","Total":"4165","New":"224","Deaths":"70 ","NewDeath":"6","Recovered":"24","Active":0,"Critical":"4071","TotalPerM":0,"TDeathPerM":"365","Tests":"6","TestPerM":"8488"},{"index":86,"DateTime":"2020\/06\/14,04:02:10","Country":"Hungary","Total":"4064","New":0,"Deaths":"559 ","NewDeath":0,"Recovered":"2476","Active":0,"Critical":"1029","TotalPerM":"20","TDeathPerM":"421","Tests":"58","TestPerM":"230139"},{"index":87,"DateTime":"2020\/06\/14,04:02:10","Country":"Luxembourg","Total":"4063","New":0,"Deaths":"110 ","NewDeath":0,"Recovered":"3922","Active":0,"Critical":"31","TotalPerM":0,"TDeathPerM":"6496","Tests":"176","TestPerM":"106062"},{"index":88,"DateTime":"2020\/06\/14,04:02:10","Country":"North Macedonia","Total":"3895","New":0,"Deaths":"179 ","NewDeath":0,"Recovered":"1705","Active":0,"Critical":"2011","TotalPerM":"34","TDeathPerM":"1870","Tests":"86","TestPerM":"42262"},{"index":89,"DateTime":"2020\/06\/14,04:02:10","Country":"El Salvador","Total":"3603","New":0,"Deaths":"72 ","NewDeath":0,"Recovered":"1738","Active":0,"Critical":"1793","TotalPerM":"126","TDeathPerM":"556","Tests":"11","TestPerM":"120941"},{"index":90,"DateTime":"2020\/06\/14,04:02:10","Country":"Gabon","Total":"3463","New":0,"Deaths":"23 ","NewDeath":0,"Recovered":"1024","Active":0,"Critical":"2416","TotalPerM":"17","TDeathPerM":"1558","Tests":"10","TestPerM":"19517"},{"index":91,"DateTime":"2020\/06\/14,04:02:10","Country":"Kenya","Total":"3457","New":0,"Deaths":"100 ","NewDeath":0,"Recovered":"1221","Active":0,"Critical":"2136","TotalPerM":"7","TDeathPerM":"64","Tests":"2","TestPerM":"112171"},{"index":92,"DateTime":"2020\/06\/14,04:02:10","Country":"Bulgaria","Total":"3266","New":0,"Deaths":"172 ","NewDeath":0,"Recovered":"1723","Active":0,"Critical":"1371","TotalPerM":"16","TDeathPerM":"470","Tests":"25","TestPerM":"103077"},{"index":93,"DateTime":"2020\/06\/14,04:02:10","Country":"Ethiopia","Total":"3166","New":0,"Deaths":"55 ","NewDeath":0,"Recovered":"495","Active":0,"Critical":"2616","TotalPerM":"39","TDeathPerM":"28","Tests":"0.5","TestPerM":"176504"},{"index":94,"DateTime":"2020\/06\/14,04:02:10","Country":"Thailand","Total":"3134","New":0,"Deaths":"58 ","NewDeath":0,"Recovered":"2987","Active":0,"Critical":"89","TotalPerM":"1","TDeathPerM":"45","Tests":"0.8","TestPerM":"468175"},{"index":95,"DateTime":"2020\/06\/14,04:02:10","Country":"Greece","Total":"3112","New":0,"Deaths":"183 ","NewDeath":0,"Recovered":"1374","Active":0,"Critical":"1555","TotalPerM":"13","TDeathPerM":"299","Tests":"18","TestPerM":"247452"},{"index":96,"DateTime":"2020\/06\/14,04:02:10","Country":"Venezuela","Total":"2904","New":0,"Deaths":"24 ","NewDeath":0,"Recovered":"487","Active":0,"Critical":"2393","TotalPerM":"1","TDeathPerM":"102","Tests":"0.8","TestPerM":"1066791"},{"index":97,"DateTime":"2020\/06\/14,04:02:10","Country":"Bosnia and Herzegovina","Total":"2893","New":0,"Deaths":"163 ","NewDeath":0,"Recovered":"2119","Active":0,"Critical":"611","TotalPerM":"4","TDeathPerM":"882","Tests":"50","TestPerM":"75171"},{"index":98,"DateTime":"2020\/06\/14,04:02:10","Country":"Somalia","Total":"2579","New":0,"Deaths":"87 ","NewDeath":0,"Recovered":"559","Active":0,"Critical":"1933","TotalPerM":"2","TDeathPerM":"163","Tests":"5","TestPerM":0},{"index":99,"DateTime":"2020\/06\/14,04:02:10","Country":"Mayotte","Total":"2282","New":0,"Deaths":"28 ","NewDeath":0,"Recovered":"1790","Active":0,"Critical":"464","TotalPerM":"12","TDeathPerM":"8376","Tests":"103","TestPerM":"8800"},{"index":100,"DateTime":"2020\/06\/14,04:02:10","Country":"Croatia","Total":"2251","New":0,"Deaths":"107 ","NewDeath":0,"Recovered":"2134","Active":0,"Critical":"10","TotalPerM":0,"TDeathPerM":"548","Tests":"26","TestPerM":"69967"},{"index":101,"DateTime":"2020\/06\/14,04:02:10","Country":"Cuba","Total":"2238","New":0,"Deaths":"84 ","NewDeath":0,"Recovered":"1923","Active":0,"Critical":"231","TotalPerM":"5","TDeathPerM":"198","Tests":"7","TestPerM":"131628"},{"index":102,"DateTime":"2020\/06\/14,04:02:10","Country":"Kyrgyzstan","Total":"2207","New":0,"Deaths":"27 ","NewDeath":0,"Recovered":"1722","Active":0,"Critical":"458","TotalPerM":"11","TDeathPerM":"339","Tests":"4","TestPerM":"147454"},{"index":103,"DateTime":"2020\/06\/14,04:02:10","Country":"CAR","Total":"2057","New":0,"Deaths":"7 ","NewDeath":0,"Recovered":"363","Active":0,"Critical":"1687","TotalPerM":"2","TDeathPerM":"426","Tests":"1","TestPerM":"18921"},{"index":104,"DateTime":"2020\/06\/14,04:02:10","Country":"Maldives","Total":"2013","New":0,"Deaths":"8 ","NewDeath":0,"Recovered":"1217","Active":0,"Critical":"788","TotalPerM":"9","TDeathPerM":"3727","Tests":"15","TestPerM":"28940"},{"index":105,"DateTime":"2020\/06\/14,04:02:10","Country":"Estonia","Total":"1973","New":0,"Deaths":"69 ","NewDeath":0,"Recovered":"1705","Active":0,"Critical":"199","TotalPerM":0,"TDeathPerM":"1487","Tests":"52","TestPerM":"95000"},{"index":106,"DateTime":"2020\/06\/14,04:02:10","Country":"Sri Lanka","Total":"1884","New":0,"Deaths":"11 ","NewDeath":0,"Recovered":"1252","Active":0,"Critical":"621","TotalPerM":"1","TDeathPerM":"88","Tests":"0.5","TestPerM":"85967"},{"index":107,"DateTime":"2020\/06\/14,04:02:10","Country":"Iceland","Total":"1808","New":0,"Deaths":"10 ","NewDeath":0,"Recovered":"1794","Active":0,"Critical":"4","TotalPerM":0,"TDeathPerM":"5300","Tests":"29","TestPerM":"63124"},{"index":108,"DateTime":"2020\/06\/14,04:02:10","Country":"Mali","Total":"1776","New":0,"Deaths":"104 ","NewDeath":0,"Recovered":"1058","Active":0,"Critical":"614","TotalPerM":0,"TDeathPerM":"88","Tests":"5","TestPerM":"3483"},{"index":109,"DateTime":"2020\/06\/14,04:02:10","Country":"Lithuania","Total":"1763","New":0,"Deaths":"75 ","NewDeath":0,"Recovered":"1416","Active":0,"Critical":"272","TotalPerM":"17","TDeathPerM":"647","Tests":"28","TestPerM":"360670"},{"index":110,"DateTime":"2020\/06\/14,04:02:10","Country":"South Sudan","Total":"1693","New":0,"Deaths":"27 ","NewDeath":0,"Recovered":"49","Active":0,"Critical":"1617","TotalPerM":0,"TDeathPerM":"151","Tests":"2","TestPerM":"3356"},{"index":111,"DateTime":"2020\/06\/14,04:02:10","Country":"Mauritania","Total":"1682","New":0,"Deaths":"83 ","NewDeath":0,"Recovered":"311","Active":0,"Critical":"1288","TotalPerM":"25","TDeathPerM":"362","Tests":"18","TestPerM":"7654"},{"index":112,"DateTime":"2020\/06\/14,04:02:10","Country":"Costa Rica","Total":"1662","New":0,"Deaths":"12 ","NewDeath":0,"Recovered":"743","Active":0,"Critical":"907","TotalPerM":"3","TDeathPerM":"326","Tests":"2","TestPerM":"31763"},{"index":113,"DateTime":"2020\/06\/14,04:02:10","Country":"Slovakia","Total":"1545","New":0,"Deaths":"28 ","NewDeath":0,"Recovered":"1410","Active":0,"Critical":"107","TotalPerM":0,"TDeathPerM":"283","Tests":"5","TestPerM":"196244"},{"index":114,"DateTime":"2020\/06\/14,04:02:10","Country":"New Zealand","Total":"1504","New":0,"Deaths":"22 ","NewDeath":0,"Recovered":"1482","Active":0,"Critical":"0","TotalPerM":0,"TDeathPerM":"301","Tests":"4","TestPerM":"310297"},{"index":115,"DateTime":"2020\/06\/14,04:02:10","Country":"Slovenia","Total":"1492","New":0,"Deaths":"109 ","NewDeath":0,"Recovered":"1359","Active":0,"Critical":"24","TotalPerM":0,"TDeathPerM":"718","Tests":"52","TestPerM":"88463"},{"index":116,"DateTime":"2020\/06\/14,04:02:10","Country":"Nicaragua","Total":"1464","New":0,"Deaths":"55 ","NewDeath":0,"Recovered":"953","Active":0,"Critical":"456","TotalPerM":0,"TDeathPerM":"221","Tests":"8","TestPerM":0},{"index":117,"DateTime":"2020\/06\/14,04:02:10","Country":"Albania","Total":"1464","New":0,"Deaths":"36 ","NewDeath":0,"Recovered":"1039","Active":0,"Critical":"389","TotalPerM":"7","TDeathPerM":"509","Tests":"13","TestPerM":"17888"},{"index":118,"DateTime":"2020\/06\/14,04:02:10","Country":"Guinea-Bissau","Total":"1460","New":0,"Deaths":"15 ","NewDeath":0,"Recovered":"153","Active":0,"Critical":"1292","TotalPerM":"5","TDeathPerM":"743","Tests":"8","TestPerM":"1500"},{"index":119,"DateTime":"2020\/06\/14,04:02:10","Country":"Lebanon","Total":"1442","New":0,"Deaths":"32  ","NewDeath":0,"Recovered":"868","Active":0,"Critical":"542","TotalPerM":"9","TDeathPerM":"211","Tests":"5","TestPerM":"105264"},{"index":120,"DateTime":"2020\/06\/14,04:02:10","Country":"Zambia","Total":"1357","New":0,"Deaths":"10 ","NewDeath":0,"Recovered":"1104","Active":0,"Critical":"243","TotalPerM":"1","TDeathPerM":"74","Tests":"0.5","TestPerM":"28236"},{"index":121,"DateTime":"2020\/06\/14,04:02:10","Country":"Equatorial Guinea","Total":"1306","New":0,"Deaths":"12 ","NewDeath":0,"Recovered":"200","Active":0,"Critical":"1094","TotalPerM":0,"TDeathPerM":"933","Tests":"9","TestPerM":"8268"},{"index":122,"DateTime":"2020\/06\/14,04:02:10","Country":"Paraguay","Total":"1261","New":0,"Deaths":"11 ","NewDeath":0,"Recovered":"647","Active":0,"Critical":"603","TotalPerM":"2","TDeathPerM":"177","Tests":"2","TestPerM":"46608"},{"index":123,"DateTime":"2020\/06\/14,04:02:10","Country":"Madagascar","Total":"1252","New":0,"Deaths":"10 ","NewDeath":0,"Recovered":"362","Active":0,"Critical":"880","TotalPerM":"9","TDeathPerM":"45","Tests":"0.4","TestPerM":"15495"},{"index":124,"DateTime":"2020\/06\/14,04:02:10","Country":"French Guiana","Total":"1161","New":0,"Deaths":"2 ","NewDeath":0,"Recovered":"520","Active":0,"Critical":"639","TotalPerM":"6","TDeathPerM":"3893","Tests":"7","TestPerM":"277"},{"index":125,"DateTime":"2020\/06\/14,04:02:10","Country":"Sierra Leone","Total":"1132","New":0,"Deaths":"51 ","NewDeath":0,"Recovered":"670","Active":0,"Critical":"411","TotalPerM":0,"TDeathPerM":"142","Tests":"6","TestPerM":0},{"index":126,"DateTime":"2020\/06\/14,04:02:10","Country":"Hong Kong","Total":"1110","New":0,"Deaths":"4 ","NewDeath":0,"Recovered":"1061","Active":0,"Critical":"45","TotalPerM":"3","TDeathPerM":"148","Tests":"0.5","TestPerM":"241992"},{"index":127,"DateTime":"2020\/06\/14,04:02:10","Country":"Latvia","Total":"1097","New":0,"Deaths":"28 ","NewDeath":0,"Recovered":"845","Active":0,"Critical":"224","TotalPerM":"1","TDeathPerM":"581","Tests":"15","TestPerM":"126054"},{"index":128,"DateTime":"2020\/06\/14,04:02:10","Country":"Tunisia","Total":"1094","New":0,"Deaths":"49 ","NewDeath":0,"Recovered":"995","Active":0,"Critical":"50","TotalPerM":0,"TDeathPerM":"93","Tests":"4","TestPerM":"58770"},{"index":129,"DateTime":"2020\/06\/14,04:02:10","Country":"Niger","Total":"980","New":0,"Deaths":"66 ","NewDeath":0,"Recovered":"881","Active":0,"Critical":"33","TotalPerM":0,"TDeathPerM":"41","Tests":"3","TestPerM":"6275"},{"index":130,"DateTime":"2020\/06\/14,04:02:10","Country":"Cyprus","Total":"980","New":0,"Deaths":"18 ","NewDeath":0,"Recovered":"807","Active":0,"Critical":"155","TotalPerM":"4","TDeathPerM":"812","Tests":"15","TestPerM":"140126"},{"index":131,"DateTime":"2020\/06\/14,04:02:10","Country":"Jordan","Total":"953","New":0,"Deaths":"9 ","NewDeath":0,"Recovered":"678","Active":0,"Critical":"266","TotalPerM":"5","TDeathPerM":"93","Tests":"0.9","TestPerM":"266873"},{"index":132,"DateTime":"2020\/06\/14,04:02:10","Country":"Burkina Faso","Total":"892","New":0,"Deaths":"53 ","NewDeath":0,"Recovered":"799","Active":0,"Critical":"40","TotalPerM":0,"TDeathPerM":"43","Tests":"3","TestPerM":0},{"index":133,"DateTime":"2020\/06\/14,04:02:10","Country":"Andorra","Total":"853","New":0,"Deaths":"51 ","NewDeath":0,"Recovered":"781","Active":0,"Critical":"21","TotalPerM":"8","TDeathPerM":"11041","Tests":"660","TestPerM":"3750"},{"index":134,"DateTime":"2020\/06\/14,04:02:10","Country":"Georgia","Total":"851","New":0,"Deaths":"14 ","NewDeath":0,"Recovered":"702","Active":0,"Critical":"135","TotalPerM":"6","TDeathPerM":"213","Tests":"4","TestPerM":"73893"},{"index":135,"DateTime":"2020\/06\/14,04:02:10","Country":"Chad","Total":"848","New":0,"Deaths":"72 ","NewDeath":0,"Recovered":"718","Active":0,"Critical":"58","TotalPerM":0,"TDeathPerM":"52","Tests":"4","TestPerM":0},{"index":136,"DateTime":"2020\/06\/14,04:02:10","Country":"Uruguay","Total":"847","New":0,"Deaths":"23 ","NewDeath":0,"Recovered":"784","Active":0,"Critical":"40","TotalPerM":"3","TDeathPerM":"244","Tests":"7","TestPerM":"52862"},{"index":137,"DateTime":"2020\/06\/14,04:02:10","Country":"Congo","Total":"728","New":0,"Deaths":"24 ","NewDeath":0,"Recovered":"221","Active":0,"Critical":"483","TotalPerM":0,"TDeathPerM":"132","Tests":"4","TestPerM":0},{"index":138,"DateTime":"2020\/06\/14,04:02:10","Country":"Cabo Verde","Total":"726","New":0,"Deaths":"6 ","NewDeath":0,"Recovered":"294","Active":0,"Critical":"426","TotalPerM":0,"TDeathPerM":"1306","Tests":"11","TestPerM":"1307"},{"index":139,"DateTime":"2020\/06\/14,04:02:10","Country":"Diamond Princess","Total":"712","New":0,"Deaths":"13 ","NewDeath":0,"Recovered":"651","Active":0,"Critical":"48","TotalPerM":"4","TDeathPerM":0,"Tests":0,"TestPerM":0},{"index":140,"DateTime":"2020\/06\/14,04:02:10","Country":"Yemen","Total":"705","New":0,"Deaths":"160 ","NewDeath":0,"Recovered":"39","Active":0,"Critical":"506","TotalPerM":0,"TDeathPerM":"24","Tests":"5","TestPerM":"120"},{"index":141,"DateTime":"2020\/06\/14,04:02:10","Country":"San Marino","Total":"694","New":0,"Deaths":"42 ","NewDeath":0,"Recovered":"520","Active":0,"Critical":"132","TotalPerM":"1","TDeathPerM":"20455","Tests":"1238","TestPerM":"5238"},{"index":142,"DateTime":"2020\/06\/14,04:02:10","Country":"Uganda","Total":"694","New":0,"Deaths":0,"NewDeath":0,"Recovered":"219","Active":0,"Critical":"475","TotalPerM":0,"TDeathPerM":"15","Tests":0,"TestPerM":"142819"},{"index":143,"DateTime":"2020\/06\/14,04:02:10","Country":"Sao Tome and Principe","Total":"659","New":0,"Deaths":"12 ","NewDeath":0,"Recovered":"176","Active":0,"Critical":"471","TotalPerM":0,"TDeathPerM":"3010","Tests":"55","TestPerM":"1453"},{"index":144,"DateTime":"2020\/06\/14,04:02:10","Country":"Malta","Total":"646","New":0,"Deaths":"9 ","NewDeath":0,"Recovered":"601","Active":0,"Critical":"36","TotalPerM":"1","TDeathPerM":"1463","Tests":"20","TestPerM":"80953"},{"index":145,"DateTime":"2020\/06\/14,04:02:10","Country":"Jamaica","Total":"615","New":"1","Deaths":"10 ","NewDeath":0,"Recovered":"420","Active":"3","Critical":"185","TotalPerM":"2","TDeathPerM":"208","Tests":"3","TestPerM":"16347"},{"index":146,"DateTime":"2020\/06\/14,04:02:10","Country":"Channel Islands","Total":"565","New":0,"Deaths":"48 ","NewDeath":0,"Recovered":"512","Active":0,"Critical":"5","TotalPerM":0,"TDeathPerM":"3251","Tests":"276","TestPerM":"10255"},{"index":147,"DateTime":"2020\/06\/14,04:02:10","Country":"Mozambique","Total":"553","New":0,"Deaths":"2 ","NewDeath":0,"Recovered":"151","Active":0,"Critical":"400","TotalPerM":0,"TDeathPerM":"18","Tests":"0.06","TestPerM":"18061"},{"index":148,"DateTime":"2020\/06\/14,04:02:10","Country":"Rwanda","Total":"541","New":0,"Deaths":"2 ","NewDeath":0,"Recovered":"332","Active":0,"Critical":"207","TotalPerM":0,"TDeathPerM":"42","Tests":"0.2","TestPerM":"87656"},{"index":149,"DateTime":"2020\/06\/14,04:02:10","Country":"Togo","Total":"530","New":0,"Deaths":"13 ","NewDeath":0,"Recovered":"291","Active":0,"Critical":"226","TotalPerM":"1","TDeathPerM":"64","Tests":"2","TestPerM":"25401"},{"index":150,"DateTime":"2020\/06\/14,04:02:10","Country":"Malawi","Total":"529","New":0,"Deaths":"5 ","NewDeath":0,"Recovered":"66","Active":0,"Critical":"458","TotalPerM":"4","TDeathPerM":"28","Tests":"0.3","TestPerM":"6690"},{"index":151,"DateTime":"2020\/06\/14,04:02:10","Country":"Tanzania","Total":"509","New":0,"Deaths":"21 ","NewDeath":0,"Recovered":"183","Active":0,"Critical":"305","TotalPerM":"7","TDeathPerM":"9","Tests":"0.4","TestPerM":0},{"index":152,"DateTime":"2020\/06\/14,04:02:10","Country":"Palestine","Total":"489","New":0,"Deaths":"3 ","NewDeath":0,"Recovered":"415","Active":0,"Critical":"71","TotalPerM":0,"TDeathPerM":"96","Tests":"0.6","TestPerM":"44876"},{"index":153,"DateTime":"2020\/06\/14,04:02:10","Country":"R\u00e9union","Total":"489","New":0,"Deaths":"1 ","NewDeath":0,"Recovered":"460","Active":0,"Critical":"28","TotalPerM":"2","TDeathPerM":"546","Tests":"1","TestPerM":"17200"},{"index":154,"DateTime":"2020\/06\/14,04:02:10","Country":"Eswatini","Total":"486","New":0,"Deaths":"3 ","NewDeath":0,"Recovered":"247","Active":0,"Critical":"236","TotalPerM":"5","TDeathPerM":"419","Tests":"3","TestPerM":"6551"},{"index":155,"DateTime":"2020\/06\/14,04:02:10","Country":"Liberia","Total":"446","New":0,"Deaths":"32 ","NewDeath":0,"Recovered":"214","Active":0,"Critical":"200","TotalPerM":0,"TDeathPerM":"88","Tests":"6","TestPerM":0},{"index":156,"DateTime":"2020\/06\/14,04:02:10","Country":"Taiwan","Total":"443","New":0,"Deaths":"7 ","NewDeath":0,"Recovered":"431","Active":0,"Critical":"5","TotalPerM":0,"TDeathPerM":"19","Tests":"0.3","TestPerM":"73751"},{"index":157,"DateTime":"2020\/06\/14,04:02:10","Country":"Libya","Total":"418","New":0,"Deaths":"8 ","NewDeath":0,"Recovered":"62","Active":0,"Critical":"348","TotalPerM":0,"TDeathPerM":"61","Tests":"1","TestPerM":"12867"},{"index":158,"DateTime":"2020\/06\/14,04:02:10","Country":"Benin","Total":"412","New":0,"Deaths":"6 ","NewDeath":0,"Recovered":"222","Active":0,"Critical":"184","TotalPerM":"2","TDeathPerM":"34","Tests":"0.5","TestPerM":"45758"},{"index":159,"DateTime":"2020\/06\/14,04:02:10","Country":"Zimbabwe","Total":"356","New":0,"Deaths":"4 ","NewDeath":0,"Recovered":"54","Active":0,"Critical":"298","TotalPerM":0,"TDeathPerM":"24","Tests":"0.3","TestPerM":"52905"},{"index":160,"DateTime":"2020\/06\/14,04:02:10","Country":"Mauritius","Total":"337","New":0,"Deaths":"10 ","NewDeath":0,"Recovered":"325","Active":0,"Critical":"2","TotalPerM":0,"TDeathPerM":"265","Tests":"8","TestPerM":"137789"},{"index":161,"DateTime":"2020\/06\/14,04:02:10","Country":"Isle of Man","Total":"336","New":0,"Deaths":"24 ","NewDeath":0,"Recovered":"312","Active":0,"Critical":"0","TotalPerM":0,"TDeathPerM":"3952","Tests":"282","TestPerM":"5484"},{"index":162,"DateTime":"2020\/06\/14,04:02:10","Country":"Vietnam","Total":"334","New":0,"Deaths":0,"NewDeath":0,"Recovered":"323","Active":0,"Critical":"11","TotalPerM":"1","TDeathPerM":"3","Tests":0,"TestPerM":"275000"},{"index":163,"DateTime":"2020\/06\/14,04:02:10","Country":"Montenegro","Total":"324","New":0,"Deaths":"9 ","NewDeath":0,"Recovered":"315","Active":0,"Critical":"0","TotalPerM":0,"TDeathPerM":"516","Tests":"14","TestPerM":"13186"},{"index":164,"DateTime":"2020\/06\/14,04:02:10","Country":"Myanmar","Total":"261","New":0,"Deaths":"6 ","NewDeath":0,"Recovered":"167","Active":0,"Critical":"88","TotalPerM":0,"TDeathPerM":"5","Tests":"0.1","TestPerM":"45926"},{"index":165,"DateTime":"2020\/06\/14,04:02:10","Country":"Martinique","Total":"202","New":0,"Deaths":"14 ","NewDeath":0,"Recovered":"98","Active":0,"Critical":"90","TotalPerM":0,"TDeathPerM":"538","Tests":"37","TestPerM":0},{"index":166,"DateTime":"2020\/06\/14,04:02:10","Country":"Mongolia","Total":"197","New":0,"Deaths":0,"NewDeath":0,"Recovered":"98","Active":"3","Critical":"99","TotalPerM":"11","TDeathPerM":"60","Tests":0,"TestPerM":"17899"},{"index":167,"DateTime":"2020\/06\/14,04:02:10","Country":"Suriname","Total":"196","New":0,"Deaths":"3 ","NewDeath":0,"Recovered":"9","Active":0,"Critical":"184","TotalPerM":"2","TDeathPerM":"334","Tests":"5","TestPerM":"1165"},{"index":168,"DateTime":"2020\/06\/14,04:02:10","Country":"Cayman Islands","Total":"187","New":0,"Deaths":"1 ","NewDeath":0,"Recovered":"115","Active":0,"Critical":"71","TotalPerM":0,"TDeathPerM":"2847","Tests":"15","TestPerM":"17227"},{"index":169,"DateTime":"2020\/06\/14,04:02:10","Country":"Faeroe Islands","Total":"187","New":0,"Deaths":0,"NewDeath":0,"Recovered":"187","Active":0,"Critical":"0","TotalPerM":0,"TDeathPerM":"3828","Tests":0,"TestPerM":"10977"},{"index":170,"DateTime":"2020\/06\/14,04:02:10","Country":"Comoros","Total":"176","New":0,"Deaths":"2 ","NewDeath":0,"Recovered":"114","Active":0,"Critical":"60","TotalPerM":0,"TDeathPerM":"203","Tests":"2","TestPerM":0},{"index":171,"DateTime":"2020\/06\/14,04:02:10","Country":"Gibraltar","Total":"176","New":0,"Deaths":0,"NewDeath":0,"Recovered":"173","Active":0,"Critical":"3","TotalPerM":0,"TDeathPerM":"5224","Tests":0,"TestPerM":"10091"},{"index":172,"DateTime":"2020\/06\/14,04:02:10","Country":"Guadeloupe","Total":"171","New":0,"Deaths":"14 ","NewDeath":0,"Recovered":"157","Active":0,"Critical":"0","TotalPerM":0,"TDeathPerM":"427","Tests":"35","TestPerM":"5691"},{"index":173,"DateTime":"2020\/06\/14,04:02:10","Country":"Syria","Total":"170","New":0,"Deaths":"6 ","NewDeath":0,"Recovered":"71","Active":0,"Critical":"93","TotalPerM":0,"TDeathPerM":"10","Tests":"0.3","TestPerM":0},{"index":174,"DateTime":"2020\/06\/14,04:02:10","Country":"Guyana","Total":"159","New":0,"Deaths":"12 ","NewDeath":0,"Recovered":"95","Active":0,"Critical":"52","TotalPerM":"1","TDeathPerM":"202","Tests":"15","TestPerM":"1927"},{"index":175,"DateTime":"2020\/06\/14,04:02:10","Country":"Bermuda","Total":"142","New":0,"Deaths":"9 ","NewDeath":0,"Recovered":"127","Active":0,"Critical":"6","TotalPerM":"2","TDeathPerM":"2280","Tests":"144","TestPerM":"8430"},{"index":176,"DateTime":"2020\/06\/14,04:02:10","Country":"Brunei ","Total":"141","New":0,"Deaths":"2 ","NewDeath":0,"Recovered":"138","Active":0,"Critical":"1","TotalPerM":"1","TDeathPerM":"322","Tests":"5","TestPerM":"24131"},{"index":177,"DateTime":"2020\/06\/14,04:02:10","Country":"Angola","Total":"138","New":0,"Deaths":"6 ","NewDeath":0,"Recovered":"61","Active":0,"Critical":"71","TotalPerM":"1","TDeathPerM":"4","Tests":"0.2","TestPerM":"10000"},{"index":178,"DateTime":"2020\/06\/14,04:02:10","Country":"Cambodia","Total":"128","New":"2","Deaths":0,"NewDeath":0,"Recovered":"125","Active":0,"Critical":"3","TotalPerM":"1","TDeathPerM":"8","Tests":0,"TestPerM":"27274"},{"index":179,"DateTime":"2020\/06\/14,04:02:10","Country":"Trinidad and Tobago","Total":"117","New":0,"Deaths":"8 ","NewDeath":0,"Recovered":"109","Active":0,"Critical":"0","TotalPerM":0,"TDeathPerM":"84","Tests":"6","TestPerM":"3876"},{"index":180,"DateTime":"2020\/06\/14,04:02:10","Country":"Bahamas","Total":"103","New":0,"Deaths":"11 ","NewDeath":0,"Recovered":"68","Active":0,"Critical":"24","TotalPerM":"1","TDeathPerM":"262","Tests":"28","TestPerM":"2261"},{"index":181,"DateTime":"2020\/06\/14,04:02:10","Country":"Aruba","Total":"101","New":0,"Deaths":"3 ","NewDeath":0,"Recovered":"98","Active":0,"Critical":"0","TotalPerM":0,"TDeathPerM":"946","Tests":"28","TestPerM":"2220"},{"index":182,"DateTime":"2020\/06\/14,04:02:10","Country":"Monaco","Total":"99","New":0,"Deaths":"4 ","NewDeath":0,"Recovered":"93","Active":0,"Critical":"2","TotalPerM":0,"TDeathPerM":"2524","Tests":"102","TestPerM":"16200"},{"index":183,"DateTime":"2020\/06\/14,04:02:10","Country":"Barbados","Total":"96","New":0,"Deaths":"7 ","NewDeath":0,"Recovered":"83","Active":0,"Critical":"6","TotalPerM":"1","TDeathPerM":"334","Tests":"24","TestPerM":"6449"},{"index":184,"DateTime":"2020\/06\/14,04:02:10","Country":"Burundi","Total":"85","New":0,"Deaths":"1 ","NewDeath":0,"Recovered":"45","Active":0,"Critical":"39","TotalPerM":0,"TDeathPerM":"7","Tests":"0.08","TestPerM":"382"},{"index":185,"DateTime":"2020\/06\/14,04:02:10","Country":"Liechtenstein","Total":"82","New":0,"Deaths":"1 ","NewDeath":0,"Recovered":"55","Active":0,"Critical":"26","TotalPerM":0,"TDeathPerM":"2151","Tests":"26","TestPerM":"900"},{"index":186,"DateTime":"2020\/06\/14,04:02:10","Country":"Sint Maarten","Total":"77","New":0,"Deaths":"15 ","NewDeath":0,"Recovered":"61","Active":0,"Critical":"1","TotalPerM":"1","TDeathPerM":"1797","Tests":"350","TestPerM":"471"},{"index":187,"DateTime":"2020\/06\/14,04:02:10","Country":"Bhutan","Total":"66","New":"4","Deaths":0,"NewDeath":0,"Recovered":"21","Active":"1","Critical":"45","TotalPerM":0,"TDeathPerM":"86","Tests":0,"TestPerM":"20731"},{"index":188,"DateTime":"2020\/06\/14,04:02:10","Country":"Eritrea","Total":"65","New":0,"Deaths":0,"NewDeath":0,"Recovered":"39","Active":0,"Critical":"26","TotalPerM":0,"TDeathPerM":"18","Tests":0,"TestPerM":0},{"index":189,"DateTime":"2020\/06\/14,04:02:10","Country":"Botswana","Total":"60","New":0,"Deaths":"1 ","NewDeath":0,"Recovered":"24","Active":0,"Critical":"35","TotalPerM":"1","TDeathPerM":"26","Tests":"0.4","TestPerM":"26800"},{"index":190,"DateTime":"2020\/06\/14,04:02:10","Country":"French Polynesia","Total":"60","New":0,"Deaths":0,"NewDeath":0,"Recovered":"60","Active":0,"Critical":"0","TotalPerM":0,"TDeathPerM":"214","Tests":0,"TestPerM":"4262"},{"index":191,"DateTime":"2020\/06\/14,04:02:10","Country":"Macao","Total":"45","New":0,"Deaths":0,"NewDeath":0,"Recovered":"45","Active":0,"Critical":"0","TotalPerM":0,"TDeathPerM":"69","Tests":0,"TestPerM":0},{"index":192,"DateTime":"2020\/06\/14,04:02:10","Country":"Saint Martin","Total":"42","New":0,"Deaths":"3 ","NewDeath":0,"Recovered":"36","Active":0,"Critical":"3","TotalPerM":"1","TDeathPerM":"1087","Tests":"78","TestPerM":"685"},{"index":193,"DateTime":"2020\/06\/14,04:02:10","Country":"Namibia","Total":"32","New":0,"Deaths":0,"NewDeath":0,"Recovered":"17","Active":0,"Critical":"15","TotalPerM":"1","TDeathPerM":"13","Tests":0,"TestPerM":"5682"},{"index":194,"DateTime":"2020\/06\/14,04:02:10","Country":"Gambia","Total":"28","New":0,"Deaths":"1 ","NewDeath":0,"Recovered":"24","Active":0,"Critical":"3","TotalPerM":0,"TDeathPerM":"12","Tests":"0.4","TestPerM":"1970"},{"index":195,"DateTime":"2020\/06\/14,04:02:10","Country":"St. Vincent Grenadines","Total":"27","New":0,"Deaths":0,"NewDeath":0,"Recovered":"25","Active":0,"Critical":"2","TotalPerM":0,"TDeathPerM":"243","Tests":0,"TestPerM":"643"},{"index":196,"DateTime":"2020\/06\/14,04:02:10","Country":"Antigua and Barbuda","Total":"26","New":0,"Deaths":"3 ","NewDeath":0,"Recovered":"20","Active":0,"Critical":"3","TotalPerM":"1","TDeathPerM":"266","Tests":"31","TestPerM":"489"},{"index":197,"DateTime":"2020\/06\/14,04:02:10","Country":"Timor-Leste","Total":"24","New":0,"Deaths":0,"NewDeath":0,"Recovered":"24","Active":0,"Critical":"0","TotalPerM":0,"TDeathPerM":"18","Tests":0,"TestPerM":"1568"},{"index":198,"DateTime":"2020\/06\/14,04:02:10","Country":"Grenada","Total":"23","New":0,"Deaths":0,"NewDeath":0,"Recovered":"22","Active":0,"Critical":"1","TotalPerM":"1","TDeathPerM":"204","Tests":0,"TestPerM":"4130"},{"index":199,"DateTime":"2020\/06\/14,04:02:10","Country":"Cura\u00e7ao","Total":"22","New":0,"Deaths":"1 ","NewDeath":0,"Recovered":"15","Active":0,"Critical":"6","TotalPerM":0,"TDeathPerM":"134","Tests":"6","TestPerM":"1080"},{"index":200,"DateTime":"2020\/06\/14,04:02:10","Country":"New Caledonia","Total":"21","New":0,"Deaths":0,"NewDeath":0,"Recovered":"20","Active":0,"Critical":"1","TotalPerM":0,"TDeathPerM":"74","Tests":0,"TestPerM":"7582"},{"index":201,"DateTime":"2020\/06\/14,04:02:10","Country":"Belize","Total":"20","New":0,"Deaths":"2 ","NewDeath":0,"Recovered":"16","Active":0,"Critical":"2","TotalPerM":0,"TDeathPerM":"50","Tests":"5","TestPerM":"1776"},{"index":202,"DateTime":"2020\/06\/14,04:02:10","Country":"Laos","Total":"19","New":0,"Deaths":0,"NewDeath":0,"Recovered":"19","Active":0,"Critical":"0","TotalPerM":0,"TDeathPerM":"3","Tests":0,"TestPerM":"9703"},{"index":203,"DateTime":"2020\/06\/14,04:02:10","Country":"Saint Lucia","Total":"19","New":0,"Deaths":0,"NewDeath":0,"Recovered":"18","Active":0,"Critical":"1","TotalPerM":0,"TDeathPerM":"103","Tests":0,"TestPerM":"1264"},{"index":204,"DateTime":"2020\/06\/14,04:02:10","Country":"Dominica","Total":"18","New":0,"Deaths":0,"NewDeath":0,"Recovered":"16","Active":0,"Critical":"2","TotalPerM":0,"TDeathPerM":"250","Tests":0,"TestPerM":"534"},{"index":205,"DateTime":"2020\/06\/14,04:02:10","Country":"Fiji","Total":"18","New":0,"Deaths":0,"NewDeath":0,"Recovered":"18","Active":0,"Critical":"0","TotalPerM":0,"TDeathPerM":"20","Tests":0,"TestPerM":"2431"},{"index":206,"DateTime":"2020\/06\/14,04:02:10","Country":"Saint Kitts and Nevis","Total":"15","New":0,"Deaths":0,"NewDeath":0,"Recovered":"15","Active":0,"Critical":"0","TotalPerM":0,"TDeathPerM":"282","Tests":0,"TestPerM":"417"},{"index":207,"DateTime":"2020\/06\/14,04:02:10","Country":"Falkland Islands","Total":"13","New":0,"Deaths":0,"NewDeath":0,"Recovered":"13","Active":0,"Critical":"0","TotalPerM":0,"TDeathPerM":"3742","Tests":0,"TestPerM":"671"},{"index":208,"DateTime":"2020\/06\/14,04:02:10","Country":"Greenland","Total":"13","New":0,"Deaths":0,"NewDeath":0,"Recovered":"13","Active":0,"Critical":"0","TotalPerM":0,"TDeathPerM":"229","Tests":0,"TestPerM":"2511"},{"index":209,"DateTime":"2020\/06\/14,04:02:10","Country":"Turks and Caicos","Total":"12","New":0,"Deaths":"1 ","NewDeath":0,"Recovered":"11","Active":0,"Critical":"0","TotalPerM":0,"TDeathPerM":"310","Tests":"26","TestPerM":"192"},{"index":210,"DateTime":"2020\/06\/14,04:02:10","Country":"Vatican City","Total":"12","New":0,"Deaths":0,"NewDeath":0,"Recovered":"12","Active":0,"Critical":"0","TotalPerM":0,"TDeathPerM":"14981","Tests":0,"TestPerM":0},{"index":211,"DateTime":"2020\/06\/14,04:02:10","Country":"Montserrat","Total":"11","New":0,"Deaths":"1 ","NewDeath":0,"Recovered":"10","Active":0,"Critical":"0","TotalPerM":0,"TDeathPerM":"2204","Tests":"200","TestPerM":"61"},{"index":212,"DateTime":"2020\/06\/14,04:02:10","Country":"Seychelles","Total":"11","New":0,"Deaths":0,"NewDeath":0,"Recovered":"11","Active":0,"Critical":"0","TotalPerM":0,"TDeathPerM":"112","Tests":0,"TestPerM":0},{"index":213,"DateTime":"2020\/06\/14,04:02:10","Country":"MS Zaandam","Total":"9","New":0,"Deaths":"2 ","NewDeath":0,"Recovered":0,"Active":0,"Critical":"7","TotalPerM":0,"TDeathPerM":0,"Tests":0,"TestPerM":0},{"index":214,"DateTime":"2020\/06\/14,04:02:10","Country":"Western Sahara","Total":"9","New":0,"Deaths":"1 ","NewDeath":0,"Recovered":"8","Active":"2","Critical":"0","TotalPerM":0,"TDeathPerM":"15","Tests":"2","TestPerM":0},{"index":215,"DateTime":"2020\/06\/14,04:02:10","Country":"British Virgin Islands","Total":"8","New":0,"Deaths":"1 ","NewDeath":0,"Recovered":"7","Active":0,"Critical":"0","TotalPerM":0,"TDeathPerM":"265","Tests":"33","TestPerM":"212"},{"index":216,"DateTime":"2020\/06\/14,04:02:10","Country":"Papua New Guinea","Total":"8","New":0,"Deaths":0,"NewDeath":0,"Recovered":"8","Active":0,"Critical":"0","TotalPerM":0,"TDeathPerM":"0.9","Tests":0,"TestPerM":"5281"},{"index":217,"DateTime":"2020\/06\/14,04:02:10","Country":"Caribbean Netherlands","Total":"7","New":0,"Deaths":0,"NewDeath":0,"Recovered":"7","Active":0,"Critical":"0","TotalPerM":0,"TDeathPerM":"267","Tests":0,"TestPerM":"424"},{"index":218,"DateTime":"2020\/06\/14,04:02:10","Country":"St. Barth","Total":"6","New":0,"Deaths":0,"NewDeath":0,"Recovered":"6","Active":0,"Critical":"0","TotalPerM":0,"TDeathPerM":"608","Tests":0,"TestPerM":"152"},{"index":219,"DateTime":"2020\/06\/14,04:02:10","Country":"Lesotho","Total":"4","New":0,"Deaths":0,"NewDeath":0,"Recovered":"2","Active":0,"Critical":"2","TotalPerM":0,"TDeathPerM":"2","Tests":0,"TestPerM":"1515"},{"index":220,"DateTime":"2020\/06\/14,04:02:10","Country":"Anguilla","Total":"3","New":0,"Deaths":0,"NewDeath":0,"Recovered":"3","Active":0,"Critical":"0","TotalPerM":0,"TDeathPerM":"200","Tests":0,"TestPerM":"41"},{"index":221,"DateTime":"2020\/06\/14,04:02:10","Country":"Saint Pierre Miquelon","Total":"1","New":0,"Deaths":0,"NewDeath":0,"Recovered":"1","Active":0,"Critical":"0","TotalPerM":0,"TDeathPerM":"173","Tests":0,"TestPerM":0},{"index":222,"DateTime":"2020\/06\/14,04:02:10","Country":"China","Total":"83132","New":"57","Deaths":"4634 ","NewDeath":0,"Recovered":"78369","Active":"2","Critical":"129","TotalPerM":0,"TDeathPerM":"58","Tests":"3","TestPerM":0}]}