{"0":{"State":"Andaman and Nicobar Islands","Confirmed":"33","Recovered":"33","Death":"0"},"1":{"State":"Andhra Pradesh","Confirmed":"2709","Recovered":"1763","Death":"55"},"2":{"State":"Arunachal Pradesh","Confirmed":"1","Recovered":"1","Death":"0"},"3":{"State":"Assam","Confirmed":"259","Recovered":"54","Death":"4"},"4":{"State":"Bihar","Confirmed":"2177","Recovered":"629","Death":"11"},"5":{"State":"Chandigarh","Confirmed":"218","Recovered":"178","Death":"3"},"6":{"State":"Chhattisgarh","Confirmed":"172","Recovered":"62","Death":"0"},"35":{"State":"Dadra and Nagar Haveli","Confirmed":"1","Recovered":"0","Death":"0"},"36":{"State":"Daman and Diu","Confirmed":0,"Recovered":0,"Death":0},"7":{"State":"Delhi","Confirmed":"12319","Recovered":"5897","Death":"208"},"8":{"State":"Goa","Confirmed":"54","Recovered":"16","Death":"0"},"9":{"State":"Gujarat","Confirmed":"13268","Recovered":"5880","Death":"802"},"10":{"State":"Haryana","Confirmed":"1067","Recovered":"706","Death":"16"},"11":{"State":"Himachal Pradesh","Confirmed":"168","Recovered":"59","Death":"3"},"12":{"State":"Jammu and Kashmir","Confirmed":"1489","Recovered":"720","Death":"20"},"13":{"State":"Jharkhand","Confirmed":"308","Recovered":"136","Death":"3"},"14":{"State":"Karnataka","Confirmed":"1743","Recovered":"597","Death":"41"},"15":{"State":"Kerala","Confirmed":"732","Recovered":"512","Death":"4"},"16":{"State":"Ladakh","Confirmed":"44","Recovered":"43","Death":"0"},"30":{"State":"Lakshadweep Islands","Confirmed":0,"Recovered":0,"Death":0},"17":{"State":"Madhya Pradesh","Confirmed":"6170","Recovered":"3089","Death":"272"},"18":{"State":"Maharashtra","Confirmed":"44582","Recovered":"12583","Death":"1517"},"19":{"State":"Manipur","Confirmed":"26","Recovered":"2","Death":"0"},"31":{"State":"Meghalaya","Confirmed":"14","Recovered":"12","Death":"1"},"20":{"State":"Mizoram","Confirmed":"1","Recovered":"1","Death":"0"},"32":{"State":"Nagaland","Confirmed":0,"Recovered":0,"Death":0},"21":{"State":"Odisha","Confirmed":"1189","Recovered":"436","Death":"7"},"22":{"State":"Puducherry","Confirmed":"26","Recovered":"10","Death":"0"},"23":{"State":"Punjab","Confirmed":"2029","Recovered":"1847","Death":"39"},"24":{"State":"Rajasthan","Confirmed":"6494","Recovered":"3680","Death":"153"},"33":{"State":"Sikkim","Confirmed":0,"Recovered":0,"Death":0},"25":{"State":"Tamil Nadu","Confirmed":"14753","Recovered":"7128","Death":"98"},"26":{"State":"Telengana","Confirmed":"1761","Recovered":"1043","Death":"45"},"34":{"State":"Tripura","Confirmed":"175","Recovered":"152","Death":"0"},"27":{"State":"Uttar Pradesh","Confirmed":"5735","Recovered":"3238","Death":"152"},"28":{"State":"Uttarakhand","Confirmed":"153","Recovered":"56","Death":"1"},"29":{"State":"West Bengal","Confirmed":"3332","Recovered":"1221","Death":"265"}}