{"0":{"Country":"World","LastUpdated":"2020\/09\/24,08:03:23","Total":"32110901","New":"982196","Deaths":"982196","NewDeath":"908","Recovered":"23692015","Active":"21251","Critical":"7436690"},"1":{"Country":"USA","LastUpdated":"2020\/09\/24,08:03:23","Total":"7139553","New":"206593 ","Deaths":"206593 ","NewDeath":0,"Recovered":"4398907","Active":0,"Critical":"2534053"},"2":{"Country":"India","LastUpdated":"2020\/09\/24,08:03:23","Total":"5732518","New":"91173 ","Deaths":"91173 ","NewDeath":0,"Recovered":"4674987","Active":"3137","Critical":"966358"},"3":{"Country":"UK","LastUpdated":"2020\/09\/24,08:03:23","Total":"409729","New":"41862 ","Deaths":"41862 ","NewDeath":0,"Recovered":"N\/A","Active":"N\/A","Critical":"N\/A"},"4":{"Country":"China","LastUpdated":"2020\/09\/24,08:03:23","Total":"85314","New":"4634 ","Deaths":"4634 ","NewDeath":0,"Recovered":"80513","Active":"8","Critical":"167"}}