{"0":{"Country":"World","LastUpdated":"2020\/06\/12,21:01:51","Total":"7689543","New":"426532","Deaths":"426532","NewDeath":"3446","Recovered":"3894062","Active":"58879","Critical":"3368949"},"1":{"Country":"USA","LastUpdated":"2020\/06\/12,21:01:51","Total":"2111685","New":"116719 ","Deaths":"116719 ","NewDeath":"685","Recovered":"823819","Active":"7733","Critical":"1171147"},"2":{"Country":"India","LastUpdated":"2020\/06\/12,21:01:51","Total":"309603","New":"8890 ","Deaths":"8890 ","NewDeath":"389","Recovered":"154231","Active":"7259","Critical":"146482"},"3":{"Country":"UK","LastUpdated":"2020\/06\/12,21:01:51","Total":"292950","New":"41481 ","Deaths":"41481 ","NewDeath":"202","Recovered":"N\/A","Active":"N\/A","Critical":"N\/A"},"4":{"Country":"China","LastUpdated":"2020\/06\/12,21:01:51","Total":"83064","New":"4634 ","Deaths":"4634 ","NewDeath":0,"Recovered":"78365","Active":"4","Critical":"65"}}