{"0":{"Country":"World","LastUpdated":"2020\/06\/24,23:01:41","Total":"9510157","New":"483821","Deaths":"483821","NewDeath":"4933","Recovered":"5162600","Active":"125444","Critical":"3863736"},"1":{"Country":"USA","LastUpdated":"2020\/06\/24,23:01:41","Total":"2460810","New":"124235 ","Deaths":"124235 ","NewDeath":"762","Recovered":"1033788","Active":"13407","Critical":"1302787"},"2":{"Country":"India","LastUpdated":"2020\/06\/24,23:01:41","Total":"472985","New":"14907 ","Deaths":"14907 ","NewDeath":"424","Recovered":"271688","Active":"13114","Critical":"186390"},"3":{"Country":"UK","LastUpdated":"2020\/06\/24,23:01:41","Total":"306862","New":"43081 ","Deaths":"43081 ","NewDeath":"154","Recovered":"N\/A","Active":"N\/A","Critical":"N\/A"},"4":{"Country":"China","LastUpdated":"2020\/06\/24,23:01:41","Total":"83430","New":"4634 ","Deaths":"4634 ","NewDeath":0,"Recovered":"78428","Active":"3","Critical":"368"}}