[{"Country":"World","LastUpdated":"2020\/07\/23,11:02:22","Total":"15404628","New":"631005","Deaths":"631005","NewDeath":"1647","Recovered":"9381575","Active":"36827","Critical":"5392048"},{"Country":"USA","LastUpdated":"2020\/07\/23,11:02:22","Total":"4101308","New":"146192 ","Deaths":"146192 ","NewDeath":"9","Recovered":"1943503","Active":"866","Critical":"2011613"},{"Country":"India","LastUpdated":"2020\/07\/23,11:02:22","Total":"1241654","New":"29906 ","Deaths":"29906 ","NewDeath":"16","Recovered":"784440","Active":"174","Critical":"427308"},{"Country":"UK","LastUpdated":"2020\/07\/23,11:02:22","Total":"296377","New":"45501 ","Deaths":"45501 ","NewDeath":0,"Recovered":"N\/A","Active":"N\/A","Critical":"N\/A"},{"Country":"China","LastUpdated":"2020\/07\/23,11:02:22","Total":"83729","New":"4634 ","Deaths":"4634 ","NewDeath":0,"Recovered":"78855","Active":"15","Critical":"240"}]