{"schema":{"fields":[{"name":"index","type":"integer"},{"name":"Country","type":"string"},{"name":"LastUpdated","type":"string"},{"name":"Total","type":"string"},{"name":"New","type":"string"},{"name":"Deaths","type":"string"},{"name":"NewDeath","type":"string"},{"name":"Recovered","type":"string"},{"name":"Active","type":"string"},{"name":"Critical","type":"string"}],"primaryKey":["index"],"pandas_version":"0.20.0"},"data":[{"index":0,"Country":"World","LastUpdated":"2020\/08\/08,01:02:51","Total":"19524066","New":"722959","Deaths":"722959","NewDeath":"6223","Recovered":"12533807","Active":"183306","Critical":"6267300"},{"index":1,"Country":"USA","LastUpdated":"2020\/08\/08,01:02:51","Total":"5095524","New":"164094 ","Deaths":"164094 ","NewDeath":"1290","Recovered":"2616915","Active":"40247","Critical":"2314515"},{"index":2,"Country":"India","LastUpdated":"2020\/08\/08,01:02:51","Total":"2086864","New":"42578 ","Deaths":"42578 ","NewDeath":"940","Recovered":"1427669","Active":"50285","Critical":"616617"},{"index":3,"Country":"UK","LastUpdated":"2020\/08\/08,01:02:51","Total":"309005","New":"46511 ","Deaths":"46511 ","NewDeath":"98","Recovered":"N\/A","Active":"N\/A","Critical":"N\/A"},{"index":4,"Country":"China","LastUpdated":"2020\/08\/08,01:02:51","Total":"84565","New":"4634 ","Deaths":"4634 ","NewDeath":0,"Recovered":"79088","Active":"31","Critical":"843"}]}