{"schema":{"fields":[{"name":"index","type":"integer"},{"name":"Country","type":"string"},{"name":"LastUpdated","type":"string"},{"name":"Total","type":"string"},{"name":"New","type":"string"},{"name":"Deaths","type":"string"},{"name":"NewDeath","type":"string"},{"name":"Recovered","type":"string"},{"name":"Active","type":"string"},{"name":"Critical","type":"string"}],"primaryKey":["index"],"pandas_version":"0.20.0"},"data":[{"index":0,"Country":"World","LastUpdated":"2020\/09\/15,18:03:25","Total":"29619695","New":"936074","Deaths":"936074","NewDeath":"3628","Recovered":"21421624","Active":"152186","Critical":"7261997"},{"index":1,"Country":"USA","LastUpdated":"2020\/09\/15,18:03:25","Total":"6763177","New":"199551 ","Deaths":"199551 ","NewDeath":"551","Recovered":"4042345","Active":"14519","Critical":"2521281"},{"index":2,"Country":"India","LastUpdated":"2020\/09\/15,18:03:25","Total":"5016182","New":"82075 ","Deaths":"82075 ","NewDeath":"1267","Recovered":"3937412","Active":"81166","Critical":"996695"},{"index":3,"Country":"UK","LastUpdated":"2020\/09\/15,18:03:25","Total":"374228","New":"41664 ","Deaths":"41664 ","NewDeath":"27","Recovered":"N\/A","Active":"N\/A","Critical":"N\/A"},{"index":4,"Country":"China","LastUpdated":"2020\/09\/15,18:03:25","Total":"85202","New":"4634 ","Deaths":"4634 ","NewDeath":0,"Recovered":"80426","Active":"11","Critical":"142"}]}