{"schema":{"fields":[{"name":"index","type":"integer"},{"name":"Country","type":"string"},{"name":"LastUpdated","type":"string"},{"name":"Total","type":"string"},{"name":"New","type":"string"},{"name":"Deaths","type":"string"},{"name":"NewDeath","type":"string"},{"name":"Recovered","type":"string"},{"name":"Active","type":"string"},{"name":"Critical","type":"string"}],"primaryKey":["index"],"pandas_version":"0.20.0"},"data":[{"index":0,"Country":"World","LastUpdated":"2020\/10\/08,18:04:05","Total":"36627860","New":"1064191","Deaths":"1064191","NewDeath":"4195","Recovered":"27554610","Active":"151843","Critical":"8009059"},{"index":1,"Country":"USA","LastUpdated":"2020\/10\/08,18:04:05","Total":"7794307","New":"217173 ","Deaths":"217173 ","NewDeath":"389","Recovered":"4999035","Active":"15655","Critical":"2578099"},{"index":2,"Country":"India","LastUpdated":"2020\/10\/08,18:04:05","Total":"6902775","New":"106534 ","Deaths":"106534 ","NewDeath":"980","Recovered":"5901710","Active":"77248","Critical":"894531"},{"index":3,"Country":"UK","LastUpdated":"2020\/10\/08,18:04:05","Total":"561815","New":"42592 ","Deaths":"42592 ","NewDeath":"77","Recovered":"N\/A","Active":"N\/A","Critical":"N\/A"},{"index":4,"Country":"China","LastUpdated":"2020\/10\/08,18:04:05","Total":"85500","New":"4634 ","Deaths":"4634 ","NewDeath":0,"Recovered":"80666","Active":"16","Critical":"200"}]}