{"schema":{"fields":[{"name":"index","type":"integer"},{"name":"Country","type":"string"},{"name":"LastUpdated","type":"string"},{"name":"Total","type":"string"},{"name":"New","type":"string"},{"name":"Deaths","type":"string"},{"name":"NewDeath","type":"string"},{"name":"Recovered","type":"string"},{"name":"Active","type":"string"},{"name":"Critical","type":"string"}],"primaryKey":["index"],"pandas_version":"0.20.0"},"data":[{"index":0,"Country":"World","LastUpdated":"2020\/07\/28,14:02:48","Total":"16689533","New":"657502","Deaths":"657502","NewDeath":"1419","Recovered":"10275318","Active":"48836","Critical":"5756713"},{"index":1,"Country":"USA","LastUpdated":"2020\/07\/28,14:02:48","Total":"4435113","New":"150515 ","Deaths":"150515 ","NewDeath":"71","Recovered":"2137986","Active":"1383","Critical":"2146612"},{"index":2,"Country":"India","LastUpdated":"2020\/07\/28,14:02:48","Total":"1493904","New":"33537 ","Deaths":"33537 ","NewDeath":"89","Recovered":"957044","Active":"3855","Critical":"503323"},{"index":3,"Country":"UK","LastUpdated":"2020\/07\/28,14:02:48","Total":"300111","New":"45759 ","Deaths":"45759 ","NewDeath":0,"Recovered":"N\/A","Active":"N\/A","Critical":"N\/A"},{"index":4,"Country":"China","LastUpdated":"2020\/07\/28,14:02:48","Total":"83959","New":"4634 ","Deaths":"4634 ","NewDeath":0,"Recovered":"78934","Active":"16","Critical":"391"}]}