{"schema":{"fields":[{"name":"index","type":"integer"},{"name":"Country","type":"string"},{"name":"LastUpdated","type":"string"},{"name":"Total","type":"string"},{"name":"New","type":"string"},{"name":"Deaths","type":"string"},{"name":"NewDeath","type":"string"},{"name":"Recovered","type":"string"},{"name":"Active","type":"string"},{"name":"Critical","type":"string"}],"primaryKey":["index"],"pandas_version":"0.20.0"},"data":[{"index":0,"Country":"World","LastUpdated":"2020\/07\/19,15:02:18","Total":"14468278","New":"605833","Deaths":"605833","NewDeath":"1590","Recovered":"8649654","Active":"42923","Critical":"5212791"},{"index":1,"Country":"USA","LastUpdated":"2020\/07\/19,15:02:18","Total":"3836686","New":"142893 ","Deaths":"142893 ","NewDeath":"16","Recovered":"1775491","Active":"272","Critical":"1918302"},{"index":2,"Country":"India","LastUpdated":"2020\/07\/19,15:02:18","Total":"1086476","New":"26951 ","Deaths":"26951 ","NewDeath":"123","Recovered":"684662","Active":"7032","Critical":"374863"},{"index":3,"Country":"UK","LastUpdated":"2020\/07\/19,15:02:18","Total":"294066","New":"45273 ","Deaths":"45273 ","NewDeath":0,"Recovered":"N\/A","Active":"N\/A","Critical":"N\/A"},{"index":4,"Country":"China","LastUpdated":"2020\/07\/19,15:02:18","Total":"83660","New":"4634 ","Deaths":"4634 ","NewDeath":0,"Recovered":"78775","Active":"17","Critical":"251"}]}